amps/__init__.py
amps/amps.py
amps/get_distro.sh
amps-0.0.3.dist-info/LICENSE
amps-0.0.3.dist-info/METADATA
amps-0.0.3.dist-info/WHEEL
amps-0.0.3.dist-info/entry_points.txt
amps-0.0.3.dist-info/top_level.txt
amps-0.0.3.dist-info/RECORD
